readability_mcp/__init__.py
readability_mcp/py.typed
readability_mcp/server.py
readability_mcp-0.0.1.dist-info/METADATA
readability_mcp-0.0.1.dist-info/WHEEL
readability_mcp-0.0.1.dist-info/entry_points.txt
readability_mcp-0.0.1.dist-info/RECORD
