Metadata-Version: 2.4
Name: readability-mcp
Version: 0.0.1
Summary: A Model Context Protocol (MCP) server that provides comprehensive text readability analysis using multiple established metrics. Built with FastMCP and Pydantic for reliable, structured analysis.
Requires-Python: >=3.11
Requires-Dist: mcp>=1.9.4
Requires-Dist: pydantic>=2.11.6
Requires-Dist: textblob>=0.19.0
Requires-Dist: textstat>=0.7.7
